tensorflow_hub/__init__.py
tensorflow_hub/compressed_module_resolver.py
tensorflow_hub/config.py
tensorflow_hub/estimator.py
tensorflow_hub/feature_column.py
tensorflow_hub/feature_column_v2.py
tensorflow_hub/file_utils.py
tensorflow_hub/image_module_info_pb2.py
tensorflow_hub/image_util.py
tensorflow_hub/keras_layer.py
tensorflow_hub/meta_graph_lib.py
tensorflow_hub/module.py
tensorflow_hub/module_attachment_pb2.py
tensorflow_hub/module_def_pb2.py
tensorflow_hub/module_impl.py
tensorflow_hub/module_spec.py
tensorflow_hub/module_v2.py
tensorflow_hub/native_module.py
tensorflow_hub/registry.py
tensorflow_hub/resolver.py
tensorflow_hub/saved_model_lib.py
tensorflow_hub/saved_model_module.py
tensorflow_hub/tensor_info.py
tensorflow_hub/tf_utils.py
tensorflow_hub/uncompressed_module_resolver.py
tensorflow_hub/version.py
tensorflow_hub/tools/__init__.py
tensorflow_hub/tools/make_image_classifier/__init__.py
tensorflow_hub/tools/make_image_classifier/make_image_classifier.py
tensorflow_hub/tools/make_image_classifier/make_image_classifier_lib.py
tensorflow_hub/tools/make_nearest_neighbour_index/__init__.py
tensorflow_hub/tools/make_nearest_neighbour_index/embedding_generator.py
tensorflow_hub/tools/make_nearest_neighbour_index/index_builder.py
tensorflow_hub/tools/make_nearest_neighbour_index/make_nearest_neighbour_index.py
tensorflow_hub/tools/make_nearest_neighbour_index/similarity_finder.py
tensorflow_hub-0.10.0.dist-info/LICENSE.txt
tensorflow_hub-0.10.0.dist-info/METADATA
tensorflow_hub-0.10.0.dist-info/WHEEL
tensorflow_hub-0.10.0.dist-info/entry_points.txt
tensorflow_hub-0.10.0.dist-info/top_level.txt
tensorflow_hub-0.10.0.dist-info/RECORD
